hyperdev/__init__.py
hyperdev/llmrouter/__init__.py
hyperdev/llmrouter/chat_stream.py
hyperdev/llmrouter/config.py
hyperdev/llmrouter/enums.py
hyperdev/llmrouter/exceptions.py
hyperdev/llmrouter/types.py
hyperdev/llmrouter/utils.py
hyperdev/llmrouter/integrations/__init__.py
hyperdev/llmrouter/integrations/langfuse.py
hyperdev/llmrouter/providers/__init__.py
hyperdev/llmrouter/providers/base.py
hyperdev/llmrouter/providers/claude.py
hyperdev/llmrouter/providers/gemini.py
hyperdev/llmrouter/providers/openai.py
hyperdev/llmrouter/providers/openrouter.py
hyperdev-0.1.2.dist-info/licenses/LICENSE
hyperdev-0.1.2.dist-info/METADATA
hyperdev-0.1.2.dist-info/WHEEL
hyperdev-0.1.2.dist-info/top_level.txt
hyperdev-0.1.2.dist-info/RECORD
