Metadata-Version: 2.4
Name: hyperdev
Version: 0.1.2
Summary: Unified streaming interface for multiple LLM providers
Author-email: HyperDev <dev@hyperdev.com>
License: MIT
Project-URL: Homepage, https://github.com/HyperDev/llmrouter
Project-URL: Repository, https://github.com/HyperDev/llmrouter.git
Project-URL: Issues, https://github.com/HyperDev/llmrouter/issues
Classifier: Development Status :: 3 - Alpha
Classifier: Intended Audience :: Developers
Classifier: Programming Language :: Python :: 3
Classifier: Programming Language :: Python :: 3.9
Classifier: Programming Language :: Python :: 3.10
Classifier: Programming Language :: Python :: 3.11
Classifier: Programming Language :: Python :: 3.12
Requires-Python: >=3.9
License-File: LICENSE
Requires-Dist: openai>=1.0.0
Requires-Dist: anthropic>=0.18.0
Requires-Dist: google-genai>=0.2.0
Requires-Dist: pydantic>=2.0.0
Requires-Dist: python-dotenv>=1.0.0
Provides-Extra: langfuse
Requires-Dist: langfuse>=2.0.0; extra == "langfuse"
Provides-Extra: dev
Requires-Dist: pytest>=7.0.0; extra == "dev"
Requires-Dist: pytest-cov>=4.0.0; extra == "dev"
Requires-Dist: black>=23.0.0; extra == "dev"
Requires-Dist: ruff>=0.1.0; extra == "dev"
Requires-Dist: mypy>=1.0.0; extra == "dev"
Dynamic: license-file
